discord_cli/__init__.py
discord_cli/argument_builder.py
discord_cli/command.py
discord_cli/command_system.py
discord_cli/exceptions.py
discord_cli/option_builder.py
discord_cli/parsers.py
discord_cli/permission_builder.py
discord_cli/permissions.py
discord_cli/tag_builder.py
discord_cli/validation.py
discord_cli-1.0.0.dist-info/LICENSE
discord_cli-1.0.0.dist-info/METADATA
discord_cli-1.0.0.dist-info/WHEEL
discord_cli-1.0.0.dist-info/top_level.txt
discord_cli-1.0.0.dist-info/RECORD
